c5_envelope/__init__.py
c5_envelope/simple_envelope.py
c5_envelope/simple_envelope_test.py
c5_envelope/lang/python/envelope.py
c5_envelope/lang/python/version.py
c5_envelope-1.0.21.dist-info/LICENSE
c5_envelope-1.0.21.dist-info/METADATA
c5_envelope-1.0.21.dist-info/WHEEL
c5_envelope-1.0.21.dist-info/top_level.txt
c5_envelope-1.0.21.dist-info/RECORD
