Metadata-Version: 2.1
Name: c5-envelope
Version: 1.0.21
Summary: C5-ENVELOPE Repository
Home-page: https://github.com/mabels/envelope
Author: Meno Abels
Author-email: meno.abels@adviser.com
License: UNKNOWN
Keywords: data ocean lake
Platform: UNKNOWN
Classifier: Intended Audience :: Developers
Classifier: Development Status :: 5 - Production/Stable
Classifier: Programming Language :: Python
Classifier: Programming Language :: Python :: 3
Classifier: Programming Language :: Python :: 3.6
Classifier: Programming Language :: Python :: 3.7
Classifier: Programming Language :: Python :: 3.8
Classifier: Topic :: Scientific/Engineering
Classifier: Intended Audience :: Developers
License-File: LICENSE
Requires-Dist: base58
Requires-Dist: object-graph-streamer
